{
    "helix": {
        "branch": "personal-fork",
        "description": "A post-modern modal text editor.",
        "homepage": "https://helix-editor.com",
        "owner": "kmicklas",
        "repo": "helix",
        "rev": "7a5e4d8b1614cdafada0ff6671fa2da4f196fbe5",
        "sha256": "127vr4xf7kwb3adxfr2mm9za1mwqr5wwlkw02hmrvy260pnmmnp0",
        "type": "tarball",
        "url": "https://github.com/kmicklas/helix/archive/7a5e4d8b1614cdafada0ff6671fa2da4f196fbe5.tar.gz",
        "url_template": "https://github.com/<owner>/<repo>/archive/<rev>.tar.gz"
    },
    "tree-sitter-rust": {
        "branch": "master",
        "description": "Rust grammar for tree-sitter",
        "homepage": "",
        "owner": "tree-sitter",
        "repo": "tree-sitter-rust",
        "rev": "48e053397b587de97790b055a1097b7c8a4ef846",
        "sha256": "0jc8sisfj50jra89y3p6pv0b2smn125m4nvkaidz1cnympajbpc6",
        "type": "tarball",
        "url": "https://github.com/tree-sitter/tree-sitter-rust/archive/48e053397b587de97790b055a1097b7c8a4ef846.tar.gz",
        "url_template": "https://github.com/<owner>/<repo>/archive/<rev>.tar.gz"
    }
}
